[
  {
    "taskId": 1,
    "taskName": "running",
    "taskCategory": "FLOATING",
    "taskCreated": "2012-11-03T21:17:16.429+08:00",
    "taskUpdated": "2012-11-03T21:18:16.445+08:00",
    "taskLastSync": null,
    "gCalTaskId": null,
    "isDone": false,
    "isDeleted": true
  },
  {
    "endDateTime": "2012-11-04T18:00:00.000+08:00",
    "taskId": 2,
    "taskName": "complete test",
    "taskCategory": "DEADLINE",
    "taskCreated": "2012-11-03T21:17:16.465+08:00",
    "taskUpdated": "2012-11-03T21:18:16.497+08:00",
    "taskLastSync": null,
    "gCalTaskId": null,
    "isDone": false,
    "isDeleted": false
  },
  {
    "startDateTime": "2012-11-04T07:00:00.000+08:00",
    "endDateTime": "2012-11-04T08:00:00.000+08:00",
    "taskId": 3,
    "taskName": "breakfast",
    "taskCategory": "TIMED",
    "taskCreated": "2012-11-04T02:59:04.733+08:00",
    "taskUpdated": "2012-11-04T02:59:04.733+08:00",
    "taskLastSync": null,
    "gCalTaskId": null,
    "isDone": false,
    "isDeleted": false
  },
  {
    "startDateTime": "2012-11-04T20:00:00.000+08:00",
    "endDateTime": "2012-11-04T21:00:00.000+08:00",
    "taskId": 4,
    "taskName": "squash physicals",
    "taskCategory": "TIMED",
    "taskCreated": "2012-11-04T02:59:32.797+08:00",
    "taskUpdated": "2012-11-04T02:59:32.797+08:00",
    "taskLastSync": null,
    "gCalTaskId": null,
    "isDone": false,
    "isDeleted": false
  },
  {
    "taskId": 5,
    "taskName": "CS2103 project",
    "taskCategory": "FLOATING",
    "taskCreated": "2012-11-04T02:59:49.427+08:00",
    "taskUpdated": "2012-11-04T02:59:49.427+08:00",
    "taskLastSync": null,
    "gCalTaskId": null,
    "isDone": false,
    "isDeleted": false
  },
  {
    "taskId": 6,
    "taskName": "buy batteries",
    "taskCategory": "FLOATING",
    "taskCreated": "2012-11-04T03:00:19.367+08:00",
    "taskUpdated": "2012-11-04T03:00:19.367+08:00",
    "taskLastSync": null,
    "gCalTaskId": null,
    "isDone": false,
    "isDeleted": false
  },
  {
    "startDateTime": "2012-11-04T14:00:00.000+08:00",
    "endDateTime": "2012-11-04T16:00:00.000+08:00",
    "taskId": 7,
    "taskName": "AP meet",
    "taskCategory": "TIMED",
    "taskCreated": "2012-11-04T03:18:03.814+08:00",
    "taskUpdated": "2012-11-04T13:19:06.487+08:00",
    "taskLastSync": null,
    "gCalTaskId": null,
    "isDone": false,
    "isDeleted": true
  },
  {
    "endDateTime": "2012-11-05T16:00:00.000+08:00",
    "taskId": 8,
    "taskName": "submission",
    "taskCategory": "DEADLINE",
    "taskCreated": "2012-11-04T03:18:50.998+08:00",
    "taskUpdated": "2012-11-04T03:22:52.055+08:00",
    "taskLastSync": null,
    "gCalTaskId": null,
    "isDone": false,
    "isDeleted": true
  },
  {
    "taskId": 9,
    "taskName": "hello",
    "taskCategory": "FLOATING",
    "taskCreated": "2012-11-04T04:26:27.166+08:00",
    "taskUpdated": "2012-11-04T04:27:34.915+08:00",
    "taskLastSync": null,
    "gCalTaskId": null,
    "isDone": false,
    "isDeleted": true
  },
  {
    "taskId": 10,
    "taskName": "Default task",
    "taskCategory": "FLOATING",
    "taskCreated": "2012-11-04T04:27:48.556+08:00",
    "taskUpdated": "2012-11-04T04:29:10.311+08:00",
    "taskLastSync": null,
    "gCalTaskId": null,
    "isDone": false,
    "isDeleted": true
  },
  {
    "startDateTime": "2012-11-04T14:00:00.000+08:00",
    "endDateTime": "2012-11-04T16:00:00.000+08:00",
    "taskId": 11,
    "taskName": "AP meet",
    "taskCategory": "TIMED",
    "taskCreated": "2012-11-04T13:18:08.535+08:00",
    "taskUpdated": "2012-11-04T13:19:21.778+08:00",
    "taskLastSync": null,
    "gCalTaskId": null,
    "isDone": false,
    "isDeleted": true
  },
  {
    "startDateTime": "2012-11-04T14:00:00.000+08:00",
    "endDateTime": "2012-11-04T16:00:00.000+08:00",
    "taskId": 12,
    "taskName": "AP meet",
    "taskCategory": "TIMED",
    "taskCreated": "2012-11-04T13:18:27.135+08:00",
    "taskUpdated": "2012-11-04T13:20:11.031+08:00",
    "taskLastSync": null,
    "gCalTaskId": null,
    "isDone": false,
    "isDeleted": true
  },
  {
    "taskId": 13,
    "taskName": "task fs",
    "taskCategory": "FLOATING",
    "taskCreated": "2012-11-04T13:18:38.186+08:00",
    "taskUpdated": "2012-11-04T13:19:56.809+08:00",
    "taskLastSync": null,
    "gCalTaskId": null,
    "isDone": false,
    "isDeleted": true
  },
  {
    "taskId": 14,
    "taskName": "task sd",
    "taskCategory": "FLOATING",
    "taskCreated": "2012-11-04T13:18:42.222+08:00",
    "taskUpdated": "2012-11-04T13:20:01.839+08:00",
    "taskLastSync": null,
    "gCalTaskId": null,
    "isDone": false,
    "isDeleted": true
  },
  {
    "startDateTime": "2012-11-04T14:00:00.000+08:00",
    "endDateTime": "2012-11-04T16:00:00.000+08:00",
    "taskId": 15,
    "taskName": "AP meet",
    "taskCategory": "TIMED",
    "taskCreated": "2012-11-04T13:19:14.784+08:00",
    "taskUpdated": "2012-11-04T13:19:14.784+08:00",
    "taskLastSync": null,
    "gCalTaskId": null,
    "isDone": false,
    "isDeleted": false
  }
]