[
  {
    "gCalTaskId": null,
    "gCalTaskUid": null,
    "endDateTime": "2012-11-11T15:00:00.000+08:00",
    "taskId": 1,
    "taskName": "timed task hi!",
    "taskCategory": "DEADLINE",
    "taskCreated": "2012-11-10T19:29:58.326+08:00",
    "taskUpdated": "2012-11-10T19:29:58.326+08:00",
    "taskLastSync": null,
    "isDone": false,
    "isDeleted": false
  },
  {
    "gTaskId": null,
    "taskId": 2,
    "taskName": "task",
    "taskCategory": "FLOATING",
    "taskCreated": "2012-11-10T19:30:10.598+08:00",
    "taskUpdated": "2012-11-10T19:31:20.283+08:00",
    "taskLastSync": null,
    "isDone": false,
    "isDeleted": true
  },
  {
    "gTaskId": null,
    "taskId": 3,
    "taskName": "asd",
    "taskCategory": "FLOATING",
    "taskCreated": "2012-11-10T19:30:11.542+08:00",
    "taskUpdated": "2012-11-10T19:30:11.542+08:00",
    "taskLastSync": null,
    "isDone": false,
    "isDeleted": false
  },
  {
    "gTaskId": null,
    "taskId": 4,
    "taskName": "s",
    "taskCategory": "FLOATING",
    "taskCreated": "2012-11-10T19:30:12.047+08:00",
    "taskUpdated": "2012-11-10T19:30:12.047+08:00",
    "taskLastSync": null,
    "isDone": false,
    "isDeleted": false
  },
  {
    "gTaskId": null,
    "taskId": 5,
    "taskName": "s",
    "taskCategory": "FLOATING",
    "taskCreated": "2012-11-10T19:30:12.225+08:00",
    "taskUpdated": "2012-11-10T19:30:12.225+08:00",
    "taskLastSync": null,
    "isDone": false,
    "isDeleted": false
  },
  {
    "gTaskId": null,
    "taskId": 6,
    "taskName": "asdfasf",
    "taskCategory": "FLOATING",
    "taskCreated": "2012-11-10T19:30:12.578+08:00",
    "taskUpdated": "2012-11-10T19:30:12.578+08:00",
    "taskLastSync": null,
    "isDone": false,
    "isDeleted": false
  },
  {
    "gTaskId": null,
    "taskId": 7,
    "taskName": "d",
    "taskCategory": "FLOATING",
    "taskCreated": "2012-11-10T19:30:12.764+08:00",
    "taskUpdated": "2012-11-10T19:30:12.764+08:00",
    "taskLastSync": null,
    "isDone": false,
    "isDeleted": false
  },
  {
    "gCalTaskId": null,
    "gCalTaskUid": null,
    "endDateTime": "2012-11-10T22:00:00.000+08:00",
    "taskId": 8,
    "taskName": "timed task",
    "taskCategory": "DEADLINE",
    "taskCreated": "2012-11-10T19:31:23.945+08:00",
    "taskUpdated": "2012-11-10T19:31:23.945+08:00",
    "taskLastSync": null,
    "isDone": false,
    "isDeleted": false
  },
  {
    "gCalTaskId": null,
    "gCalTaskUid": null,
    "endDateTime": "2012-11-11T15:00:00.000+08:00",
    "taskId": 9,
    "taskName": "timed task",
    "taskCategory": "DEADLINE",
    "taskCreated": "2012-11-10T19:31:46.514+08:00",
    "taskUpdated": "2012-11-10T19:31:46.514+08:00",
    "taskLastSync": null,
    "isDone": false,
    "isDeleted": false
  },
  {
    "gCalTaskId": null,
    "gCalTaskUid": null,
    "endDateTime": "2012-11-11T15:00:00.000+08:00",
    "taskId": 10,
    "taskName": "new task",
    "taskCategory": "DEADLINE",
    "taskCreated": "2012-11-10T19:32:43.696+08:00",
    "taskUpdated": "2012-11-10T21:00:48.180+08:00",
    "taskLastSync": null,
    "isDone": false,
    "isDeleted": true
  },
  {
    "gCalTaskId": null,
    "gCalTaskUid": null,
    "endDateTime": "2012-11-11T15:00:00.000+08:00",
    "taskId": 11,
    "taskName": "task",
    "taskCategory": "DEADLINE",
    "taskCreated": "2012-11-10T19:34:08.370+08:00",
    "taskUpdated": "2012-11-10T19:34:08.370+08:00",
    "taskLastSync": null,
    "isDone": false,
    "isDeleted": false
  },
  {
    "gCalTaskId": null,
    "gCalTaskUid": null,
    "endDateTime": "2012-11-11T15:00:00.000+08:00",
    "taskId": 12,
    "taskName": "timed task",
    "taskCategory": "DEADLINE",
    "taskCreated": "2012-11-10T19:58:44.766+08:00",
    "taskUpdated": "2012-11-10T19:58:44.766+08:00",
    "taskLastSync": null,
    "isDone": false,
    "isDeleted": false
  },
  {
    "gCalTaskId": null,
    "gCalTaskUid": null,
    "endDateTime": "2012-11-11T15:00:00.000+08:00",
    "taskId": 13,
    "taskName": "task",
    "taskCategory": "DEADLINE",
    "taskCreated": "2012-11-10T20:02:14.468+08:00",
    "taskUpdated": "2012-11-10T20:02:14.468+08:00",
    "taskLastSync": null,
    "isDone": false,
    "isDeleted": false
  },
  {
    "gCalTaskId": null,
    "gCalTaskUid": null,
    "endDateTime": "2012-11-11T15:00:00.000+08:00",
    "taskId": 14,
    "taskName": "timed task",
    "taskCategory": "DEADLINE",
    "taskCreated": "2012-11-10T20:23:03.296+08:00",
    "taskUpdated": "2012-11-10T20:23:03.296+08:00",
    "taskLastSync": null,
    "isDone": false,
    "isDeleted": false
  },
  {
    "gCalTaskId": null,
    "gCalTaskUid": null,
    "endDateTime": "2012-11-11T15:00:00.000+08:00",
    "taskId": 15,
    "taskName": "new sync task",
    "taskCategory": "DEADLINE",
    "taskCreated": "2012-11-10T20:23:42.484+08:00",
    "taskUpdated": "2012-11-10T20:26:06.767+08:00",
    "taskLastSync": null,
    "isDone": false,
    "isDeleted": false
  },
  {
    "gCalTaskId": null,
    "gCalTaskUid": null,
    "endDateTime": "2012-11-11T17:00:00.000+08:00",
    "taskId": 16,
    "taskName": "timed task",
    "taskCategory": "DEADLINE",
    "taskCreated": "2012-11-10T20:41:05.555+08:00",
    "taskUpdated": "2012-11-10T20:41:05.555+08:00",
    "taskLastSync": null,
    "isDone": false,
    "isDeleted": false
  },
  {
    "gCalTaskId": null,
    "gCalTaskUid": null,
    "endDateTime": "2012-11-10T23:00:00.000+08:00",
    "taskId": 17,
    "taskName": "timed task",
    "taskCategory": "DEADLINE",
    "taskCreated": "2012-11-10T20:42:41.121+08:00",
    "taskUpdated": "2012-11-10T20:42:41.121+08:00",
    "taskLastSync": null,
    "isDone": false,
    "isDeleted": false
  },
  {
    "gCalTaskId": null,
    "gCalTaskUid": null,
    "endDateTime": "2012-11-11T15:00:00.000+08:00",
    "taskId": 18,
    "taskName": "new task",
    "taskCategory": "DEADLINE",
    "taskCreated": "2012-11-10T20:59:32.163+08:00",
    "taskUpdated": "2012-11-10T20:59:32.163+08:00",
    "taskLastSync": null,
    "isDone": false,
    "isDeleted": false
  },
  {
    "gCalTaskId": "phjpudf8a6n1as0mmd9g10bbg0",
    "gCalTaskUid": "phjpudf8a6n1as0mmd9g10bbg0@google.com",
    "endDateTime": "2012-11-11T15:00:00.000+08:00",
    "taskId": 19,
    "taskName": "new task",
    "taskCategory": "DEADLINE",
    "taskCreated": "2012-11-11T01:42:16.121+08:00",
    "taskUpdated": "2012-11-11T01:42:16.121+08:00",
    "taskLastSync": "2012-11-11T01:43:16.000+08:00",
    "isDone": false,
    "isDeleted": false
  }
]